{
  "event_count": 32,
  "last_event_id": "01KT6ZPNSWQ10ZK78A4WE4KGYR",
  "materialized_at": "2026-06-03T14:55:19.868817+00:00",
  "mission_number": "18",
  "mission_slug": "cheap-operator-live-trial-01KT6PSA",
  "mission_type": "software-dev",
  "summary": {
    "approved": 3,
    "blocked": 0,
    "canceled": 0,
    "claimed": 0,
    "done": 2,
    "for_review": 0,
    "in_progress": 0,
    "in_review": 0,
    "planned": 0
  },
  "work_packages": {
    "WP01": {
      "actor": "user",
      "force_count": 2,
      "lane": "done",
      "last_event_id": "01KT6ZPMJEWXE1EMQT1FXMKWXA",
      "last_transition_at": "2026-06-03T14:55:18.606230+00:00"
    },
    "WP02": {
      "actor": "user",
      "force_count": 2,
      "lane": "done",
      "last_event_id": "01KT6ZPNSWQ10ZK78A4WE4KGYR",
      "last_transition_at": "2026-06-03T14:55:19.868817+00:00"
    },
    "WP03": {
      "actor": "user",
      "force_count": 1,
      "lane": "approved",
      "last_event_id": "01KT6XCCM3Q98AE5A867GSDBGE",
      "last_transition_at": "2026-06-03T14:14:45.635330+00:00"
    },
    "WP04": {
      "actor": "user",
      "force_count": 1,
      "lane": "approved",
      "last_event_id": "01KT6YCW458VT9FQWP6WAE597X",
      "last_transition_at": "2026-06-03T14:32:30.085400+00:00"
    },
    "WP05": {
      "actor": "user",
      "force_count": 1,
      "lane": "approved",
      "last_event_id": "01KT6ZC1JV2F7P0DY4RGQW4QPT",
      "last_transition_at": "2026-06-03T14:49:31.483566+00:00"
    }
  }
}
