{
  "event_count": 28,
  "last_event_id": "01KSN4N96BGADCERWDEXGPCS3J",
  "materialized_at": "2026-05-27T16:35:37.291797+00:00",
  "mission_number": "7",
  "mission_slug": "implement-profile-and-intake-storage-01KSMWV1",
  "mission_type": "software-dev",
  "summary": {
    "approved": 0,
    "blocked": 0,
    "canceled": 0,
    "claimed": 0,
    "done": 4,
    "for_review": 0,
    "in_progress": 0,
    "in_review": 0,
    "planned": 0
  },
  "work_packages": {
    "WP01": {
      "actor": "user",
      "force_count": 2,
      "lane": "done",
      "last_event_id": "01KSN4N5XDD3FVFP5BDRZ3Z5TH",
      "last_transition_at": "2026-05-27T16:35:33.933452+00:00"
    },
    "WP02": {
      "actor": "user",
      "force_count": 2,
      "lane": "done",
      "last_event_id": "01KSN4N72DBHHQ85FTHK0X7F39",
      "last_transition_at": "2026-05-27T16:35:35.117554+00:00"
    },
    "WP03": {
      "actor": "user",
      "force_count": 2,
      "lane": "done",
      "last_event_id": "01KSN4N84600QNB9S4FM9GTP7A",
      "last_transition_at": "2026-05-27T16:35:36.198172+00:00"
    },
    "WP04": {
      "actor": "user",
      "force_count": 2,
      "lane": "done",
      "last_event_id": "01KSN4N96BGADCERWDEXGPCS3J",
      "last_transition_at": "2026-05-27T16:35:37.291797+00:00"
    }
  }
}
